[
	{
		"key": "fr",
		"value": "17UK6upydQzGTeudB.AWUTrAh37WUQdlcrCr5nC1_hKd4.BfidDK.22.AAA.0.0.BfidDY.AWUwMmRiE-8",
		"domain": "facebook.com",
		"path": "/",
		"hostOnly": false,
		"creation": "2020-10-16T16:57:12.064Z",
		"lastAccessed": "2020-10-16T16:57:17.256Z"
	},
	{
		"key": "sb",
		"value": "ytCJXwJTThs5QCWNH49O52ey",
		"domain": "facebook.com",
		"path": "/",
		"hostOnly": false,
		"creation": "2020-10-16T16:57:12.084Z",
		"lastAccessed": "2020-10-16T16:57:17.256Z"
	},
	{
		"key": "datr",
		"value": "ytCJX9jFDYxwQk8bGvxwqf-O",
		"domain": "facebook.com",
		"path": "/",
		"hostOnly": false,
		"creation": "2020-10-16T16:57:12.086Z",
		"lastAccessed": "2020-10-16T16:57:17.256Z"
	},
	{
		"key": "locale",
		"value": "vi_VN",
		"domain": "facebook.com",
		"path": "/",
		"hostOnly": false,
		"creation": "2020-10-16T16:57:12.087Z",
		"lastAccessed": "2020-10-16T16:57:17.256Z"
	},
	{
		"key": "c_user",
		"value": "100050794989101",
		"domain": "facebook.com",
		"path": "/",
		"hostOnly": false,
		"creation": "2020-10-16T16:57:12.088Z",
		"lastAccessed": "2020-10-16T16:57:17.256Z"
	},
	{
		"key": "xs",
		"value": "12%3Ao-eJmpa9fJ-3Cw%3A2%3A1602867417%3A10647%3A5735",
		"domain": "facebook.com",
		"path": "/",
		"hostOnly": false,
		"creation": "2020-10-16T16:57:12.089Z",
		"lastAccessed": "2020-10-16T16:57:17.256Z"
	},
	{
		"key": "fr",
		"value": "17UK6upydQzGTeudB.AWUTrAh37WUQdlcrCr5nC1_hKd4.BfidDK.22.AAA.0.0.BfidDY.AWUwMmRiE-8",
		"domain": "facebook.com",
		"path": "/",
		"hostOnly": false,
		"creation": "2020-10-16T16:57:12.064Z",
		"lastAccessed": "2020-10-16T16:57:17.256Z"
	},
	{
		"key": "sb",
		"value": "ytCJXwJTThs5QCWNH49O52ey",
		"domain": "facebook.com",
		"path": "/",
		"hostOnly": false,
		"creation": "2020-10-16T16:57:12.084Z",
		"lastAccessed": "2020-10-16T16:57:17.256Z"
	},
	{
		"key": "datr",
		"value": "ytCJX9jFDYxwQk8bGvxwqf-O",
		"domain": "facebook.com",
		"path": "/",
		"hostOnly": false,
		"creation": "2020-10-16T16:57:12.086Z",
		"lastAccessed": "2020-10-16T16:57:17.256Z"
	},
	{
		"key": "locale",
		"value": "vi_VN",
		"domain": "facebook.com",
		"path": "/",
		"hostOnly": false,
		"creation": "2020-10-16T16:57:12.087Z",
		"lastAccessed": "2020-10-16T16:57:17.256Z"
	},
	{
		"key": "c_user",
		"value": "100050794989101",
		"domain": "facebook.com",
		"path": "/",
		"hostOnly": false,
		"creation": "2020-10-16T16:57:12.088Z",
		"lastAccessed": "2020-10-16T16:57:17.256Z"
	},
	{
		"key": "xs",
		"value": "12%3Ao-eJmpa9fJ-3Cw%3A2%3A1602867417%3A10647%3A5735",
		"domain": "facebook.com",
		"path": "/",
		"hostOnly": false,
		"creation": "2020-10-16T16:57:12.089Z",
		"lastAccessed": "2020-10-16T16:57:17.256Z"
	},
	{
		"key": "fr",
		"value": "17UK6upydQzGTeudB.AWUTrAh37WUQdlcrCr5nC1_hKd4.BfidDK.22.AAA.0.0.BfidDY.AWUwMmRiE-8",
		"domain": "messenger.com",
		"path": "/",
		"hostOnly": false,
		"creation": "2020-10-16T16:57:12.092Z",
		"lastAccessed": "2020-10-16T16:57:17.257Z"
	},
	{
		"key": "sb",
		"value": "ytCJXwJTThs5QCWNH49O52ey",
		"domain": "messenger.com",
		"path": "/",
		"hostOnly": false,
		"creation": "2020-10-16T16:57:12.092Z",
		"lastAccessed": "2020-10-16T16:57:17.257Z"
	},
	{
		"key": "locale",
		"value": "vi_VN",
		"domain": "messenger.com",
		"path": "/",
		"hostOnly": false,
		"creation": "2020-10-16T16:57:12.092Z",
		"lastAccessed": "2020-10-16T16:57:17.257Z"
	},
	{
		"key": "c_user",
		"value": "100050794989101",
		"domain": "messenger.com",
		"path": "/",
		"hostOnly": false,
		"creation": "2020-10-16T16:57:12.093Z",
		"lastAccessed": "2020-10-16T16:57:17.257Z"
	},
	{
		"key": "xs",
		"value": "12%3Ao-eJmpa9fJ-3Cw%3A2%3A1602867417%3A10647%3A5735",
		"domain": "messenger.com",
		"path": "/",
		"hostOnly": false,
		"creation": "2020-10-16T16:57:12.093Z",
		"lastAccessed": "2020-10-16T16:57:17.257Z"
	}
]